{"tilemap": {"0;13": {"type": "stone", "variant": 6, "pos": [0, 13]}, "1;13": {"type": "stone", "variant": 5, "pos": [1, 13]}, "2;13": {"type": "stone", "variant": 5, "pos": [2, 13]}, "3;13": {"type": "stone", "variant": 5, "pos": [3, 13]}, "4;13": {"type": "stone", "variant": 5, "pos": [4, 13]}, "5;13": {"type": "stone", "variant": 5, "pos": [5, 13]}, "6;13": {"type": "stone", "variant": 5, "pos": [6, 13]}, "7;13": {"type": "stone", "variant": 5, "pos": [7, 13]}, "8;13": {"type": "stone", "variant": 5, "pos": [8, 13]}, "8;12": {"type": "stone", "variant": 1, "pos": [8, 12]}, "7;12": {"type": "stone", "variant": 1, "pos": [7, 12]}, "6;12": {"type": "stone", "variant": 1, "pos": [6, 12]}, "5;12": {"type": "stone", "variant": 1, "pos": [5, 12]}, "4;12": {"type": "stone", "variant": 1, "pos": [4, 12]}, "3;12": {"type": "stone", "variant": 1, "pos": [3, 12]}, "2;12": {"type": "stone", "variant": 1, "pos": [2, 12]}, "1;12": {"type": "stone", "variant": 1, "pos": [1, 12]}, "0;12": {"type": "stone", "variant": 0, "pos": [0, 12]}, "9;13": {"type": "stone", "variant": 5, "pos": [9, 13]}, "9;12": {"type": "stone", "variant": 1, "pos": [9, 12]}, "10;12": {"type": "stone", "variant": 1, "pos": [10, 12]}, "11;12": {"type": "stone", "variant": 1, "pos": [11, 12]}, "11;13": {"type": "stone", "variant": 5, "pos": [11, 13]}, "10;13": {"type": "stone", "variant": 5, "pos": [10, 13]}, "12;13": {"type": "stone", "variant": 5, "pos": [12, 13]}, "13;13": {"type": "stone", "variant": 5, "pos": [13, 13]}, "13;12": {"type": "stone", "variant": 1, "pos": [13, 12]}, "12;12": {"type": "stone", "variant": 1, "pos": [12, 12]}, "14;12": {"type": "stone", "variant": 1, "pos": [14, 12]}, "15;12": {"type": "stone", "variant": 2, "pos": [15, 12]}, "15;13": {"type": "stone", "variant": 4, "pos": [15, 13]}, "14;13": {"type": "stone", "variant": 5, "pos": [14, 13]}, "21;13": {"type": "stone", "variant": 6, "pos": [21, 13]}, "21;12": {"type": "stone", "variant": 0, "pos": [21, 12]}, "22;12": {"type": "stone", "variant": 1, "pos": [22, 12]}, "23;12": {"type": "stone", "variant": 1, "pos": [23, 12]}, "24;12": {"type": "stone", "variant": 2, "pos": [24, 12]}, "24;13": {"type": "stone", "variant": 4, "pos": [24, 13]}, "23;13": {"type": "stone", "variant": 5, "pos": [23, 13]}, "22;13": {"type": "stone", "variant": 5, "pos": [22, 13]}, "28;10": {"type": "stone", "variant": 6, "pos": [28, 10]}, "29;10": {"type": "stone", "variant": 5, "pos": [29, 10]}, "30;10": {"type": "stone", "variant": 5, "pos": [30, 10]}, "31;10": {"type": "stone", "variant": 5, "pos": [31, 10]}, "32;10": {"type": "stone", "variant": 4, "pos": [32, 10]}, "32;9": {"type": "stone", "variant": 2, "pos": [32, 9]}, "31;9": {"type": "stone", "variant": 1, "pos": [31, 9]}, "30;9": {"type": "stone", "variant": 1, "pos": [30, 9]}, "29;9": {"type": "stone", "variant": 1, "pos": [29, 9]}, "28;9": {"type": "stone", "variant": 0, "pos": [28, 9]}, "26;5": {"type": "stone", "variant": 4, "pos": [26, 5]}, "25;5": {"type": "stone", "variant": 5, "pos": [25, 5]}, "24;5": {"type": "stone", "variant": 5, "pos": [24, 5]}, "23;5": {"type": "stone", "variant": 5, "pos": [23, 5]}, "22;5": {"type": "stone", "variant": 5, "pos": [22, 5]}, "22;4": {"type": "stone", "variant": 8, "pos": [22, 4]}, "23;4": {"type": "stone", "variant": 1, "pos": [23, 4]}, "24;4": {"type": "stone", "variant": 1, "pos": [24, 4]}, "26;4": {"type": "stone", "variant": 2, "pos": [26, 4]}, "25;4": {"type": "stone", "variant": 1, "pos": [25, 4]}, "21;4": {"type": "stone", "variant": 8, "pos": [21, 4]}, "21;5": {"type": "stone", "variant": 5, "pos": [21, 5]}, "20;4": {"type": "stone", "variant": 7, "pos": [20, 4]}, "20;3": {"type": "stone", "variant": 7, "pos": [20, 3]}, "21;3": {"type": "stone", "variant": 8, "pos": [21, 3]}, "22;3": {"type": "stone", "variant": 3, "pos": [22, 3]}, "22;2": {"type": "stone", "variant": 2, "pos": [22, 2]}, "21;2": {"type": "stone", "variant": 8, "pos": [21, 2]}, "20;2": {"type": "stone", "variant": 7, "pos": [20, 2]}, "20;1": {"type": "stone", "variant": 7, "pos": [20, 1]}, "21;1": {"type": "stone", "variant": 3, "pos": [21, 1]}, "21;0": {"type": "stone", "variant": 2, "pos": [21, 0]}, "20;0": {"type": "stone", "variant": 0, "pos": [20, 0]}, "20;5": {"type": "stone", "variant": 6, "pos": [20, 5]}, "12;0": {"type": "stone", "variant": 2, "pos": [12, 0]}, "11;0": {"type": "stone", "variant": 1, "pos": [11, 0]}, "10;0": {"type": "stone", "variant": 1, "pos": [10, 0]}, "9;0": {"type": "stone", "variant": 1, "pos": [9, 0]}, "8;0": {"type": "stone", "variant": 1, "pos": [8, 0]}, "7;0": {"type": "stone", "variant": 1, "pos": [7, 0]}, "6;0": {"type": "stone", "variant": 0, "pos": [6, 0]}, "6;1": {"type": "stone", "variant": 6, "pos": [6, 1]}, "7;1": {"type": "stone", "variant": 5, "pos": [7, 1]}, "8;1": {"type": "stone", "variant": 5, "pos": [8, 1]}, "9;1": {"type": "stone", "variant": 5, "pos": [9, 1]}, "10;1": {"type": "stone", "variant": 5, "pos": [10, 1]}, "11;1": {"type": "stone", "variant": 5, "pos": [11, 1]}, "12;1": {"type": "stone", "variant": 4, "pos": [12, 1]}, "2;-1": {"type": "stone", "variant": 4, "pos": [2, -1]}, "1;-1": {"type": "stone", "variant": 6, "pos": [1, -1]}, "1;-2": {"type": "stone", "variant": 7, "pos": [1, -2]}, "1;-3": {"type": "stone", "variant": 7, "pos": [1, -3]}, "1;-4": {"type": "stone", "variant": 7, "pos": [1, -4]}, "1;-5": {"type": "stone", "variant": 7, "pos": [1, -5]}, "2;-5": {"type": "stone", "variant": 3, "pos": [2, -5]}, "2;-6": {"type": "stone", "variant": 3, "pos": [2, -6]}, "2;-7": {"type": "stone", "variant": 2, "pos": [2, -7]}, "2;-2": {"type": "stone", "variant": 3, "pos": [2, -2]}, "2;-3": {"type": "stone", "variant": 3, "pos": [2, -3]}, "2;-4": {"type": "stone", "variant": 3, "pos": [2, -4]}, "1;-6": {"type": "stone", "variant": 7, "pos": [1, -6]}, "1;-7": {"type": "stone", "variant": 0, "pos": [1, -7]}, "6;-4": {"type": "stone", "variant": 6, "pos": [6, -4]}, "7;-4": {"type": "stone", "variant": 5, "pos": [7, -4]}, "8;-4": {"type": "stone", "variant": 5, "pos": [8, -4]}, "9;-4": {"type": "stone", "variant": 5, "pos": [9, -4]}, "10;-4": {"type": "stone", "variant": 5, "pos": [10, -4]}, "11;-4": {"type": "stone", "variant": 5, "pos": [11, -4]}, "12;-4": {"type": "stone", "variant": 4, "pos": [12, -4]}, "12;-5": {"type": "stone", "variant": 3, "pos": [12, -5]}, "12;-6": {"type": "stone", "variant": 2, "pos": [12, -6]}, "11;-6": {"type": "stone", "variant": 1, "pos": [11, -6]}, "10;-6": {"type": "stone", "variant": 1, "pos": [10, -6]}, "9;-6": {"type": "stone", "variant": 1, "pos": [9, -6]}, "8;-6": {"type": "stone", "variant": 1, "pos": [8, -6]}, "7;-6": {"type": "stone", "variant": 1, "pos": [7, -6]}, "6;-6": {"type": "stone", "variant": 0, "pos": [6, -6]}, "6;-5": {"type": "stone", "variant": 7, "pos": [6, -5]}, "7;-5": {"type": "stone", "variant": 8, "pos": [7, -5]}, "8;-5": {"type": "stone", "variant": 8, "pos": [8, -5]}, "9;-5": {"type": "stone", "variant": 8, "pos": [9, -5]}, "10;-5": {"type": "stone", "variant": 8, "pos": [10, -5]}, "11;-5": {"type": "stone", "variant": 8, "pos": [11, -5]}, "18;-6": {"type": "stone", "variant": 0, "pos": [18, -6]}, "19;-6": {"type": "stone", "variant": 1, "pos": [19, -6]}, "20;-6": {"type": "stone", "variant": 1, "pos": [20, -6]}, "21;-6": {"type": "stone", "variant": 1, "pos": [21, -6]}, "22;-6": {"type": "stone", "variant": 1, "pos": [22, -6]}, "23;-6": {"type": "stone", "variant": 1, "pos": [23, -6]}, "24;-6": {"type": "stone", "variant": 1, "pos": [24, -6]}, "25;-6": {"type": "stone", "variant": 1, "pos": [25, -6]}, "26;-6": {"type": "stone", "variant": 1, "pos": [26, -6]}, "26;-5": {"type": "stone", "variant": 5, "pos": [26, -5]}, "27;-5": {"type": "stone", "variant": 5, "pos": [27, -5]}, "28;-5": {"type": "stone", "variant": 5, "pos": [28, -5]}, "28;-6": {"type": "stone", "variant": 1, "pos": [28, -6]}, "27;-6": {"type": "stone", "variant": 1, "pos": [27, -6]}, "18;-5": {"type": "stone", "variant": 6, "pos": [18, -5]}, "19;-5": {"type": "stone", "variant": 5, "pos": [19, -5]}, "20;-5": {"type": "stone", "variant": 5, "pos": [20, -5]}, "21;-5": {"type": "stone", "variant": 5, "pos": [21, -5]}, "22;-5": {"type": "stone", "variant": 5, "pos": [22, -5]}, "23;-5": {"type": "stone", "variant": 5, "pos": [23, -5]}, "24;-5": {"type": "stone", "variant": 5, "pos": [24, -5]}, "25;-5": {"type": "stone", "variant": 5, "pos": [25, -5]}, "29;-6": {"type": "stone", "variant": 1, "pos": [29, -6]}, "30;-6": {"type": "stone", "variant": 8, "pos": [30, -6]}, "31;-6": {"type": "stone", "variant": 8, "pos": [31, -6]}, "29;-5": {"type": "stone", "variant": 5, "pos": [29, -5]}, "30;-5": {"type": "stone", "variant": 5, "pos": [30, -5]}, "31;-5": {"type": "stone", "variant": 5, "pos": [31, -5]}, "32;-5": {"type": "stone", "variant": 5, "pos": [32, -5]}, "32;-6": {"type": "stone", "variant": 8, "pos": [32, -6]}, "33;-6": {"type": "stone", "variant": 3, "pos": [33, -6]}, "33;-5": {"type": "stone", "variant": 4, "pos": [33, -5]}, "33;-7": {"type": "stone", "variant": 3, "pos": [33, -7]}, "32;-7": {"type": "stone", "variant": 8, "pos": [32, -7]}, "31;-7": {"type": "stone", "variant": 8, "pos": [31, -7]}, "30;-7": {"type": "stone", "variant": 7, "pos": [30, -7]}, "30;-8": {"type": "stone", "variant": 0, "pos": [30, -8]}, "31;-8": {"type": "stone", "variant": 1, "pos": [31, -8]}, "32;-8": {"type": "stone", "variant": 8, "pos": [32, -8]}, "33;-8": {"type": "stone", "variant": 3, "pos": [33, -8]}, "33;-9": {"type": "stone", "variant": 3, "pos": [33, -9]}, "32;-9": {"type": "stone", "variant": 7, "pos": [32, -9]}, "32;-10": {"type": "stone", "variant": 7, "pos": [32, -10]}, "33;-10": {"type": "stone", "variant": 3, "pos": [33, -10]}, "33;-11": {"type": "stone", "variant": 2, "pos": [33, -11]}, "32;-11": {"type": "stone", "variant": 0, "pos": [32, -11]}, "31;-9": {"type": "decor", "variant": 3, "pos": [31, -9]}, "23;-7": {"type": "decor", "variant": 3, "pos": [23, -7]}, "22;1": {"type": "decor", "variant": 3, "pos": [22, 1]}, "7;-7": {"type": "decor", "variant": 3, "pos": [7, -7]}, "5;11": {"type": "decor", "variant": 3, "pos": [5, 11]}, "36;-11": {"type": "grass", "variant": 0, "pos": [36, -11]}, "37;-11": {"type": "grass", "variant": 1, "pos": [37, -11]}, "38;-11": {"type": "grass", "variant": 1, "pos": [38, -11]}, "39;-11": {"type": "grass", "variant": 1, "pos": [39, -11]}, "40;-11": {"type": "grass", "variant": 1, "pos": [40, -11]}, "41;-11": {"type": "grass", "variant": 1, "pos": [41, -11]}, "42;-11": {"type": "grass", "variant": 1, "pos": [42, -11]}, "43;-11": {"type": "grass", "variant": 1, "pos": [43, -11]}, "44;-11": {"type": "grass", "variant": 1, "pos": [44, -11]}, "45;-11": {"type": "grass", "variant": 1, "pos": [45, -11]}, "46;-11": {"type": "grass", "variant": 1, "pos": [46, -11]}, "47;-11": {"type": "grass", "variant": 2, "pos": [47, -11]}, "44;-10": {"type": "grass", "variant": 5, "pos": [44, -10]}, "43;-10": {"type": "grass", "variant": 5, "pos": [43, -10]}, "42;-10": {"type": "grass", "variant": 5, "pos": [42, -10]}, "40;-10": {"type": "grass", "variant": 5, "pos": [40, -10]}, "39;-10": {"type": "grass", "variant": 5, "pos": [39, -10]}, "38;-10": {"type": "grass", "variant": 5, "pos": [38, -10]}, "37;-10": {"type": "grass", "variant": 5, "pos": [37, -10]}, "36;-10": {"type": "grass", "variant": 6, "pos": [36, -10]}, "41;-10": {"type": "grass", "variant": 5, "pos": [41, -10]}, "45;-10": {"type": "grass", "variant": 5, "pos": [45, -10]}, "46;-10": {"type": "grass", "variant": 5, "pos": [46, -10]}, "47;-10": {"type": "grass", "variant": 4, "pos": [47, -10]}, "50;-12": {"type": "grass", "variant": 6, "pos": [50, -12]}, "51;-12": {"type": "grass", "variant": 5, "pos": [51, -12]}, "52;-12": {"type": "grass", "variant": 5, "pos": [52, -12]}, "53;-12": {"type": "grass", "variant": 4, "pos": [53, -12]}, "53;-13": {"type": "grass", "variant": 2, "pos": [53, -13]}, "52;-13": {"type": "grass", "variant": 1, "pos": [52, -13]}, "51;-13": {"type": "grass", "variant": 1, "pos": [51, -13]}, "50;-13": {"type": "grass", "variant": 0, "pos": [50, -13]}, "44;-15": {"type": "grass", "variant": 6, "pos": [44, -15]}, "45;-15": {"type": "grass", "variant": 5, "pos": [45, -15]}, "46;-15": {"type": "grass", "variant": 5, "pos": [46, -15]}, "47;-15": {"type": "grass", "variant": 4, "pos": [47, -15]}, "47;-16": {"type": "grass", "variant": 2, "pos": [47, -16]}, "46;-16": {"type": "grass", "variant": 1, "pos": [46, -16]}, "45;-16": {"type": "grass", "variant": 1, "pos": [45, -16]}, "44;-16": {"type": "grass", "variant": 0, "pos": [44, -16]}, "51;-18": {"type": "grass", "variant": 6, "pos": [51, -18]}, "52;-18": {"type": "grass", "variant": 5, "pos": [52, -18]}, "53;-18": {"type": "grass", "variant": 5, "pos": [53, -18]}, "54;-18": {"type": "grass", "variant": 4, "pos": [54, -18]}, "54;-19": {"type": "grass", "variant": 2, "pos": [54, -19]}, "53;-19": {"type": "grass", "variant": 1, "pos": [53, -19]}, "52;-19": {"type": "grass", "variant": 1, "pos": [52, -19]}, "51;-19": {"type": "grass", "variant": 0, "pos": [51, -19]}}, "tile_size": 16, "offgrid": [{"type": "large_decor", "variant": 0, "pos": [291.5, -102.0]}, {"type": "large_decor", "variant": 0, "pos": [319.5, -99.0]}, {"type": "large_decor", "variant": 0, "pos": [407.0, -101.5]}, {"type": "large_decor", "variant": 0, "pos": [431.5, -99.0]}, {"type": "large_decor", "variant": 0, "pos": [15.0, -116.5]}, {"type": "large_decor", "variant": 0, "pos": [189.0, 187.0]}, {"type": "large_decor", "variant": 0, "pos": [449.5, 137.5]}, {"type": "large_decor", "variant": 0, "pos": [26.5, 186.0]}, {"type": "large_decor", "variant": 0, "pos": [52.5, 189.5]}, {"type": "spawners", "variant": 0, "pos": [5.5, 176.5]}, {"type": "spawners", "variant": 1, "pos": [221.5, 175.5]}, {"type": "spawners", "variant": 1, "pos": [496.5, 127.5]}, {"type": "spawners", "variant": 1, "pos": [123.0, -17.0]}, {"type": "spawners", "variant": 1, "pos": [185.5, -16.5]}, {"type": "spawners", "variant": 1, "pos": [331.0, -113.5]}, {"type": "spawners", "variant": 1, "pos": [419.0, -114.5]}, {"type": "spawners", "variant": 1, "pos": [151.5, 175.5]}, {"type": "spawners", "variant": 1, "pos": [331.0, -17.0]}, {"type": "spawners", "variant": 1, "pos": [353.5, -111.5]}, {"type": "spawners", "variant": 1, "pos": [868.5, -319.5]}, {"type": "large_decor", "variant": 2, "pos": [814.5, -347.5]}, {"type": "large_decor", "variant": 2, "pos": [820.5, -334.5]}, {"type": "large_decor", "variant": 2, "pos": [840.0, -251.0]}, {"type": "large_decor", "variant": 2, "pos": [702.0, -298.0]}, {"type": "large_decor", "variant": 2, "pos": [574.5, -219.0]}, {"type": "large_decor", "variant": 2, "pos": [673.5, -194.0]}, {"type": "large_decor", "variant": 2, "pos": [697.0, -188.0]}, {"type": "large_decor", "variant": 2, "pos": [684.5, -217.5]}, {"type": "large_decor", "variant": 2, "pos": [686.5, -186.5]}]}